Fourier_fonctions/Exercice1.py
Fourier_fonctions/Exercice2.py
Fourier_fonctions/Exercice3.py
Fourier_fonctions/Exercice4.py
Fourier_fonctions/Zero_Padding.py
Fourier_fonctions/__init__.py
Fourier_fonctions/convolution.py
Fourier_fonctions/filtre_Moyen_Mobile.py
Fourier_fonctions/fourier.py
Fourier_fonctions-0.1.2.dist-info/LICENSE
Fourier_fonctions-0.1.2.dist-info/METADATA
Fourier_fonctions-0.1.2.dist-info/WHEEL
Fourier_fonctions-0.1.2.dist-info/top_level.txt
Fourier_fonctions-0.1.2.dist-info/RECORD
